scule/__init__.py
scule/pypi.py
scule-2023.12.0.dist-info/LICENSE
scule-2023.12.0.dist-info/METADATA
scule-2023.12.0.dist-info/WHEEL
scule-2023.12.0.dist-info/entry_points.txt
scule-2023.12.0.dist-info/RECORD
